seerep/__init__.py
seerep/fb/AttributesStamped.py
seerep/fb/Boolean.py
seerep/fb/Boundingbox.py
seerep/fb/CameraIntrinsics.py
seerep/fb/CameraIntrinsicsQuery.py
seerep/fb/DatasetUuidLabel.py
seerep/fb/Datatype.py
seerep/fb/Datatypes.py
seerep/fb/Double.py
seerep/fb/Empty.py
seerep/fb/FrameQuery.py
seerep/fb/GeodeticCoordinates.py
seerep/fb/Header.py
seerep/fb/Image.py
seerep/fb/Integer.py
seerep/fb/Label.py
seerep/fb/LabelCategory.py
seerep/fb/Point.py
seerep/fb/Point2D.py
seerep/fb/PointCloud2.py
seerep/fb/PointField.py
seerep/fb/PointStamped.py
seerep/fb/Point_Field_Datatype.py
seerep/fb/Polygon2D.py
seerep/fb/ProjectCreation.py
seerep/fb/ProjectInfo.py
seerep/fb/ProjectInfos.py
seerep/fb/Quaternion.py
seerep/fb/Query.py
seerep/fb/QueryInstance.py
seerep/fb/RegionOfInterest.py
seerep/fb/ServerResponse.py
seerep/fb/SparqlQuery.py
seerep/fb/String.py
seerep/fb/StringVector.py
seerep/fb/TRANSMISSION_STATE.py
seerep/fb/TimeInterval.py
seerep/fb/Timestamp.py
seerep/fb/Transform.py
seerep/fb/TransformStamped.py
seerep/fb/TransformStampedIntervalQuery.py
seerep/fb/TransformStampedQuery.py
seerep/fb/UnionMapEntry.py
seerep/fb/UuidDatatypePair.py
seerep/fb/UuidDatatypeWithCategory.py
seerep/fb/UuidsPerProject.py
seerep/fb/UuidsProjectPair.py
seerep/fb/Vector3.py
seerep/fb/__init__.py
seerep/fb/camera_intrinsics_service_grpc_fb.py
seerep/fb/image_service_grpc_fb.py
seerep/fb/instance_service_grpc_fb.py
seerep/fb/meta_operations_grpc_fb.py
seerep/fb/point_cloud_service_grpc_fb.py
seerep/fb/point_service_grpc_fb.py
seerep/fb/tf_service_grpc_fb.py
seerep/pb/__init__.py
seerep/pb/boundingbox_pb2.py
seerep/pb/boundingbox_pb2_grpc.py
seerep/pb/camera_intrinsics_pb2.py
seerep/pb/camera_intrinsics_pb2_grpc.py
seerep/pb/camera_intrinsics_query_pb2.py
seerep/pb/camera_intrinsics_query_pb2_grpc.py
seerep/pb/camera_intrinsics_service_pb2.py
seerep/pb/camera_intrinsics_service_pb2_grpc.py
seerep/pb/datatype_pb2.py
seerep/pb/datatype_pb2_grpc.py
seerep/pb/frame_query_pb2.py
seerep_grpc-0.3.6.dist-info/LICENSE
seerep_grpc-0.3.6.dist-info/METADATA
seerep_grpc-0.3.6.dist-info/WHEEL
seerep_grpc-0.3.6.dist-info/top_level.txt
seerep_grpc-0.3.6.dist-info/RECORD
