Metadata-Version: 2.1
Name: seerep_grpc
Version: 0.3.6
Summary: Package for the SEEREP gRPC API
Author-email: Mark Niemeyer <mark.niemeyer@dfki.de>
License: BSD 3-Clause License
Project-URL: Repository, https://github.com/DFKI-NI/seerep
Project-URL: Documentation, https://dfki-ni.github.io/seerep/mkdocs/home/index.html
Keywords: SEEREP, gRPC, Protocol Buffers,Flatbuffers
Requires-Python: >=3.8
License-File: LICENSE
Requires-Dist: protobuf ==5.26.1
Requires-Dist: flatbuffers ==22.12.6
Requires-Dist: grpcio ==1.67.0
